apf/consumers/__init__.py
apf/consumers/avro_file.py
apf/consumers/csv.py
apf/consumers/generic.py
apf/consumers/json.py
apf/consumers/kafka.py
apf/core/__init__.py
apf/core/secret_manager.py
apf/core/step.py
apf/core/topic_management.py
apf/core/management/__init__.py
apf/core/management/helpers.py
apf/core/templates/step/Dockerfile
apf/core/templates/step/requirements.txt
apf/core/templates/step/settings.py
apf/core/templates/step/setup.py
apf/core/templates/step/package/__init__.py
apf/core/templates/step/package/step.py
apf/core/templates/step/scripts/run_step.py
apf/metrics/__init__.py
apf/metrics/generic.py
apf/metrics/kafka.py
apf/metrics/log.py
apf/metrics/prometheus/__init__.py
apf/metrics/prometheus/prometheus.py
apf/metrics/pyroscope/__init__.py
apf/metrics/pyroscope/profile.py
apf/producers/__init__.py
apf/producers/csv.py
apf/producers/generic.py
apf/producers/json_prod.py
apf/producers/kafka.py
apf_base-2.5.2.data/scripts/apf
apf_base-2.5.2.dist-info/LICENSE
apf_base-2.5.2.dist-info/METADATA
apf_base-2.5.2.dist-info/WHEEL
apf_base-2.5.2.dist-info/top_level.txt
apf_base-2.5.2.dist-info/RECORD
