Metadata-Version: 2.1
Name: apf-base
Version: 2.5.2
Summary: ALeRCE Alert Processing Framework.
Author: ALeRCE Team
Author-email: contact@alerce.online
Project-URL: Github, https://github.com/alercebroker/APF
Project-URL: Documentation, https://apf.readthedocs.io/en/latest/index.html
License-File: LICENSE
Requires-Dist: click (>=7.1.1)
Requires-Dist: confluent-kafka (<2.1.0,>=1.4.0)
Requires-Dist: fastavro (<=1.6.1,>=0.22.0)
Requires-Dist: Jinja2 (>=2.10.0)
Requires-Dist: pandas (<=2.0.1,>=0.24)
Requires-Dist: boto3 (==1.26.69)
Requires-Dist: prometheus-client (==0.16.0)
Requires-Dist: pyroscope-io (==0.8.4)
